{"name":"Eliminate a product","id":"buylaptop;eliminate-a-product","testSteps":[{"number":1,"description":"Given he user enter a the website","duration":11617,"startTime":"2023-09-19T22:40:54.769-05:00[America/Bogota]","screenshots":[{"screenshot":"fbd7453b7da749f1dee14da386e1f439a6d2809cda84c687952f0bcbdf3b9213.png","timeStamp":1695181266386}],"result":"SUCCESS","precondition":false,"level":0,"children":[{"number":2,"description":"Andres opens the https://www.demoblaze.com/index.html","duration":11597,"startTime":"2023-09-19T22:40:54.774-05:00[America/Bogota]","screenshots":[{"screenshot":"fbd7453b7da749f1dee14da386e1f439a6d2809cda84c687952f0bcbdf3b9213.png","timeStamp":1695181266371}],"result":"SUCCESS","precondition":false,"level":1}]},{"number":3,"description":"When the user select a product and the agregate a carrito for delete","duration":30534,"startTime":"2023-09-19T22:41:06.388-05:00[America/Bogota]","screenshots":[{"screenshot":"3c75e53580afa48443274b690f88ea219ab11c5f6fa52f305b83c374feea8d8b.png","timeStamp":1695181296922}],"result":"SUCCESS","precondition":false,"level":0,"children":[{"number":4,"description":"Andres laptop task","duration":26456,"startTime":"2023-09-19T22:41:06.410-05:00[America/Bogota]","screenshots":[{"screenshot":"8ea9d6b106fc3750e69ea82bb5986bdcae8191e71b1bfb984834a7e25bf76f43.png","timeStamp":1695181292866}],"result":"SUCCESS","precondition":false,"level":1,"children":[{"number":5,"description":"Andres clicks on Seleccionar modulo laptop","duration":931,"startTime":"2023-09-19T22:41:06.872-05:00[America/Bogota]","screenshots":[{"screenshot":"094d3c17537f65d4adfc9952b6d997467fcefe3eca866ea2861a9e55584fe8d4.png","timeStamp":1695181267188},{"screenshot":"3314486deec795ac169569477e7290d9e3606b7756fa1790a14e9dc0f65de86b.png","timeStamp":1695181267803}],"result":"SUCCESS","precondition":false,"level":2},{"number":6,"description":"Andres clicks on Seleccionar laptop","duration":8519,"startTime":"2023-09-19T22:41:07.813-05:00[America/Bogota]","screenshots":[{"screenshot":"3314486deec795ac169569477e7290d9e3606b7756fa1790a14e9dc0f65de86b.png","timeStamp":1695181267839},{"screenshot":"0bd553412de8a9d90e174a6c46a70f0b2550d4e557fc49a9713909bf61bba6a0.png","timeStamp":1695181276332}],"result":"SUCCESS","precondition":false,"level":2},{"number":7,"description":"Andres clicks on comprar laptop","duration":691,"startTime":"2023-09-19T22:41:16.337-05:00[America/Bogota]","screenshots":[{"screenshot":"0bd553412de8a9d90e174a6c46a70f0b2550d4e557fc49a9713909bf61bba6a0.png","timeStamp":1695181276353},{"screenshot":"3f2843f68cb7a2243aaf61831c4e71bde9785adb179d8b34b2d86a1853ca2758.png","timeStamp":1695181277028}],"result":"SUCCESS","precondition":false,"level":2},{"number":8,"description":"Andres clicks on ir al carrito ","duration":2492,"startTime":"2023-09-19T22:41:20.036-05:00[America/Bogota]","screenshots":[{"screenshot":"3c75e53580afa48443274b690f88ea219ab11c5f6fa52f305b83c374feea8d8b.png","timeStamp":1695181282528}],"result":"SUCCESS","precondition":false,"level":2}]},{"number":9,"description":"Andres delete product task","duration":4037,"startTime":"2023-09-19T22:41:32.875-05:00[America/Bogota]","screenshots":[{"screenshot":"8ea9d6b106fc3750e69ea82bb5986bdcae8191e71b1bfb984834a7e25bf76f43.png","timeStamp":1695181292889},{"screenshot":"3c75e53580afa48443274b690f88ea219ab11c5f6fa52f305b83c374feea8d8b.png","timeStamp":1695181296911}],"result":"SUCCESS","precondition":false,"level":1,"children":[{"number":10,"description":"Andres clicks on eliminar compra ","duration":711,"startTime":"2023-09-19T22:41:32.898-05:00[America/Bogota]","screenshots":[{"screenshot":"8ea9d6b106fc3750e69ea82bb5986bdcae8191e71b1bfb984834a7e25bf76f43.png","timeStamp":1695181292914},{"screenshot":"2bb91cecfd7b7c0f5fbc83bd1cd8545190ed19611db6276d5e2d1f4325b5f5c9.png","timeStamp":1695181293609}],"result":"SUCCESS","precondition":false,"level":2}]}]},{"number":11,"description":"Then the user see that not there is products","duration":2435,"startTime":"2023-09-19T22:41:36.923-05:00[America/Bogota]","screenshots":[{"screenshot":"3c75e53580afa48443274b690f88ea219ab11c5f6fa52f305b83c374feea8d8b.png","timeStamp":1695181299358}],"result":"SUCCESS","precondition":false,"level":0,"children":[{"number":12,"description":"Then validar contenedor should be (false)","duration":2406,"startTime":"2023-09-19T22:41:36.935-05:00[America/Bogota]","screenshots":[{"screenshot":"3c75e53580afa48443274b690f88ea219ab11c5f6fa52f305b83c374feea8d8b.png","timeStamp":1695181299341}],"result":"SUCCESS","precondition":false,"level":1}]}],"userStory":{"id":"buylaptop","storyName":"BuyLaptop","path":"src/test/resources/features/buyLaptop.feature","narrative":"  i need buy a Laptod","type":"feature"},"featureTag":{"name":"Features/BuyLaptop","type":"feature","displayName":"Features/BuyLaptop"},"title":"Eliminate a product","tags":[{"name":"BuyLaptop","type":"feature","displayName":"BuyLaptop"}],"startTime":"2023-09-19T22:40:54.759-05:00[America/Bogota]","duration":44601,"projectKey":"","sessionId":"42ee535a1cdd23022633948402ec09ec","driver":"chrome","isManualTestingUpToDate":false,"manual":false,"testSource":"Cucumber","actors":[{"name":"Andres","can":["browse the web"]}],"result":"SUCCESS"}