{"name":"Eliminate a product","id":"buylaptop;eliminate-a-product","testSteps":[{"number":1,"description":"Given he user enter a the website","duration":837,"startTime":"2023-09-19T16:48:09.612-05:00[America/Bogota]","exception":{"errorType":"net.thucydides.core.webdriver.DriverConfigurationError","message":"Could not instantiate class org.openqa.selenium.chrome.ChromeDriver","stackTrace":[{"declaringClass":"com.co.shein.stepsdefinitions.LoginStepDefiniton","methodName":"heUserEnterATheWebsite","fileName":"LoginStepDefiniton.java","lineNumber":31},{"declaringClass":"cucumber.runner.Runner","methodName":"runPickle","fileName":"Runner.java","lineNumber":80},{"declaringClass":"worker.org.gradle.process.internal.worker.GradleWorkerMain","methodName":"run","fileName":"GradleWorkerMain.java","lineNumber":69},{"declaringClass":"worker.org.gradle.process.internal.worker.GradleWorkerMain","methodName":"main","fileName":"GradleWorkerMain.java","lineNumber":74}],"rootCause":{"errorType":"net.thucydides.core.webdriver.DriverConfigurationError","message":"Could not instantiate new WebDriver instance of type class org.openqa.selenium.chrome.ChromeDriver (unknown error: failed to write prefs file\nBuild info: version: \u00273.141.59\u0027, revision: \u0027e82be7d358\u0027, time: \u00272018-11-14T08:17:03\u0027\nSystem info: host: \u0027DESKTOP-SN1JVCC\u0027, ip: \u0027192.168.56.1\u0027, os.name: \u0027Windows 10\u0027, os.arch: \u0027amd64\u0027, os.version: \u002710.0\u0027, java.version: \u00271.8.0_161\u0027\nDriver info: driver.version: ProvideNewDriver\nremote stacktrace: \tGetHandleVerifier [0x00007FF7300552A2+57122]\n\t(No symbol) [0x00007FF72FFCEA92]\n\t(No symbol) [0x00007FF72FE9E3AB]\n\t(No symbol) [0x00007FF72FEC8F12]\n\t(No symbol) [0x00007FF72FEC9201]\n\t(No symbol) [0x00007FF72FEC610F]\n\t(No symbol) [0x00007FF72FEC2FE1]\n\t(No symbol) [0x00007FF72FEFEA4F]\n\t(No symbol) [0x00007FF72FEFE5B0]\n\t(No symbol) [0x00007FF72FEF6DB3]\n\t(No symbol) [0x00007FF72FECD2B1]\n\t(No symbol) [0x00007FF72FECE494]\n\tGetHandleVerifier [0x00007FF7302FEF82+2849794]\n\tGetHandleVerifier [0x00007FF730351D24+3189156]\n\tGetHandleVerifier [0x00007FF73034ACAF+3160367]\n\tGetHandleVerifier [0x00007FF7300E6D06+653702]\n\t(No symbol) [0x00007FF72FFDA208]\n\t(No symbol) [0x00007FF72FFD62C4]\n\t(No symbol) [0x00007FF72FFD63F6]\n\t(No symbol) [0x00007FF72FFC67A3]\n\tBaseThreadInitThunk [0x00007FFAEED47614+20]\n\tRtlUserThreadStart [0x00007FFAF02E26B1+33]\n). See below for more details.","stackTrace":[{"declaringClass":"com.co.shein.stepsdefinitions.LoginStepDefiniton","methodName":"heUserEnterATheWebsite","fileName":"LoginStepDefiniton.java","lineNumber":31},{"declaringClass":"cucumber.runner.Runner","methodName":"runPickle","fileName":"Runner.java","lineNumber":80},{"declaringClass":"worker.org.gradle.process.internal.worker.GradleWorkerMain","methodName":"run","fileName":"GradleWorkerMain.java","lineNumber":69},{"declaringClass":"worker.org.gradle.process.internal.worker.GradleWorkerMain","methodName":"main","fileName":"GradleWorkerMain.java","lineNumber":74}],"rootCause":{"errorType":"org.openqa.selenium.WebDriverException","message":"unknown error: failed to write prefs file\nBuild info: version: \u00273.141.59\u0027, revision: \u0027e82be7d358\u0027, time: \u00272018-11-14T08:17:03\u0027\nSystem info: host: \u0027DESKTOP-SN1JVCC\u0027, ip: \u0027192.168.56.1\u0027, os.name: \u0027Windows 10\u0027, os.arch: \u0027amd64\u0027, os.version: \u002710.0\u0027, java.version: \u00271.8.0_161\u0027\nDriver info: driver.version: ProvideNewDriver\nremote stacktrace: \tGetHandleVerifier [0x00007FF7300552A2+57122]\n\t(No symbol) [0x00007FF72FFCEA92]\n\t(No symbol) [0x00007FF72FE9E3AB]\n\t(No symbol) [0x00007FF72FEC8F12]\n\t(No symbol) [0x00007FF72FEC9201]\n\t(No symbol) [0x00007FF72FEC610F]\n\t(No symbol) [0x00007FF72FEC2FE1]\n\t(No symbol) [0x00007FF72FEFEA4F]\n\t(No symbol) [0x00007FF72FEFE5B0]\n\t(No symbol) [0x00007FF72FEF6DB3]\n\t(No symbol) [0x00007FF72FECD2B1]\n\t(No symbol) [0x00007FF72FECE494]\n\tGetHandleVerifier [0x00007FF7302FEF82+2849794]\n\tGetHandleVerifier [0x00007FF730351D24+3189156]\n\tGetHandleVerifier [0x00007FF73034ACAF+3160367]\n\tGetHandleVerifier [0x00007FF7300E6D06+653702]\n\t(No symbol) [0x00007FF72FFDA208]\n\t(No symbol) [0x00007FF72FFD62C4]\n\t(No symbol) [0x00007FF72FFD63F6]\n\t(No symbol) [0x00007FF72FFC67A3]\n\tBaseThreadInitThunk [0x00007FFAEED47614+20]\n\tRtlUserThreadStart [0x00007FFAF02E26B1+33]\n","stackTrace":[{"declaringClass":"com.co.shein.stepsdefinitions.LoginStepDefiniton","methodName":"heUserEnterATheWebsite","fileName":"LoginStepDefiniton.java","lineNumber":31},{"declaringClass":"cucumber.runner.Runner","methodName":"runPickle","fileName":"Runner.java","lineNumber":80},{"declaringClass":"worker.org.gradle.process.internal.worker.GradleWorkerMain","methodName":"run","fileName":"GradleWorkerMain.java","lineNumber":69},{"declaringClass":"worker.org.gradle.process.internal.worker.GradleWorkerMain","methodName":"main","fileName":"GradleWorkerMain.java","lineNumber":74}]}}},"result":"ERROR","precondition":false,"level":0,"children":[{"number":2,"description":"Andres opens the https://www.demoblaze.com/index.html","duration":832,"startTime":"2023-09-19T16:48:09.614-05:00[America/Bogota]","exception":{"errorType":"net.thucydides.core.webdriver.DriverConfigurationError","message":"Could not instantiate class org.openqa.selenium.chrome.ChromeDriver","stackTrace":[{"declaringClass":"com.co.shein.stepsdefinitions.LoginStepDefiniton","methodName":"heUserEnterATheWebsite","fileName":"LoginStepDefiniton.java","lineNumber":31},{"declaringClass":"cucumber.runner.Runner","methodName":"runPickle","fileName":"Runner.java","lineNumber":80},{"declaringClass":"worker.org.gradle.process.internal.worker.GradleWorkerMain","methodName":"run","fileName":"GradleWorkerMain.java","lineNumber":69},{"declaringClass":"worker.org.gradle.process.internal.worker.GradleWorkerMain","methodName":"main","fileName":"GradleWorkerMain.java","lineNumber":74}],"rootCause":{"errorType":"net.thucydides.core.webdriver.DriverConfigurationError","message":"Could not instantiate new WebDriver instance of type class org.openqa.selenium.chrome.ChromeDriver (unknown error: failed to write prefs file\nBuild info: version: \u00273.141.59\u0027, revision: \u0027e82be7d358\u0027, time: \u00272018-11-14T08:17:03\u0027\nSystem info: host: \u0027DESKTOP-SN1JVCC\u0027, ip: \u0027192.168.56.1\u0027, os.name: \u0027Windows 10\u0027, os.arch: \u0027amd64\u0027, os.version: \u002710.0\u0027, java.version: \u00271.8.0_161\u0027\nDriver info: driver.version: ProvideNewDriver\nremote stacktrace: \tGetHandleVerifier [0x00007FF7300552A2+57122]\n\t(No symbol) [0x00007FF72FFCEA92]\n\t(No symbol) [0x00007FF72FE9E3AB]\n\t(No symbol) [0x00007FF72FEC8F12]\n\t(No symbol) [0x00007FF72FEC9201]\n\t(No symbol) [0x00007FF72FEC610F]\n\t(No symbol) [0x00007FF72FEC2FE1]\n\t(No symbol) [0x00007FF72FEFEA4F]\n\t(No symbol) [0x00007FF72FEFE5B0]\n\t(No symbol) [0x00007FF72FEF6DB3]\n\t(No symbol) [0x00007FF72FECD2B1]\n\t(No symbol) [0x00007FF72FECE494]\n\tGetHandleVerifier [0x00007FF7302FEF82+2849794]\n\tGetHandleVerifier [0x00007FF730351D24+3189156]\n\tGetHandleVerifier [0x00007FF73034ACAF+3160367]\n\tGetHandleVerifier [0x00007FF7300E6D06+653702]\n\t(No symbol) [0x00007FF72FFDA208]\n\t(No symbol) [0x00007FF72FFD62C4]\n\t(No symbol) [0x00007FF72FFD63F6]\n\t(No symbol) [0x00007FF72FFC67A3]\n\tBaseThreadInitThunk [0x00007FFAEED47614+20]\n\tRtlUserThreadStart [0x00007FFAF02E26B1+33]\n). See below for more details.","stackTrace":[{"declaringClass":"com.co.shein.stepsdefinitions.LoginStepDefiniton","methodName":"heUserEnterATheWebsite","fileName":"LoginStepDefiniton.java","lineNumber":31},{"declaringClass":"cucumber.runner.Runner","methodName":"runPickle","fileName":"Runner.java","lineNumber":80},{"declaringClass":"worker.org.gradle.process.internal.worker.GradleWorkerMain","methodName":"run","fileName":"GradleWorkerMain.java","lineNumber":69},{"declaringClass":"worker.org.gradle.process.internal.worker.GradleWorkerMain","methodName":"main","fileName":"GradleWorkerMain.java","lineNumber":74}],"rootCause":{"errorType":"org.openqa.selenium.WebDriverException","message":"unknown error: failed to write prefs file\nBuild info: version: \u00273.141.59\u0027, revision: \u0027e82be7d358\u0027, time: \u00272018-11-14T08:17:03\u0027\nSystem info: host: \u0027DESKTOP-SN1JVCC\u0027, ip: \u0027192.168.56.1\u0027, os.name: \u0027Windows 10\u0027, os.arch: \u0027amd64\u0027, os.version: \u002710.0\u0027, java.version: \u00271.8.0_161\u0027\nDriver info: driver.version: ProvideNewDriver\nremote stacktrace: \tGetHandleVerifier [0x00007FF7300552A2+57122]\n\t(No symbol) [0x00007FF72FFCEA92]\n\t(No symbol) [0x00007FF72FE9E3AB]\n\t(No symbol) [0x00007FF72FEC8F12]\n\t(No symbol) [0x00007FF72FEC9201]\n\t(No symbol) [0x00007FF72FEC610F]\n\t(No symbol) [0x00007FF72FEC2FE1]\n\t(No symbol) [0x00007FF72FEFEA4F]\n\t(No symbol) [0x00007FF72FEFE5B0]\n\t(No symbol) [0x00007FF72FEF6DB3]\n\t(No symbol) [0x00007FF72FECD2B1]\n\t(No symbol) [0x00007FF72FECE494]\n\tGetHandleVerifier [0x00007FF7302FEF82+2849794]\n\tGetHandleVerifier [0x00007FF730351D24+3189156]\n\tGetHandleVerifier [0x00007FF73034ACAF+3160367]\n\tGetHandleVerifier [0x00007FF7300E6D06+653702]\n\t(No symbol) [0x00007FF72FFDA208]\n\t(No symbol) [0x00007FF72FFD62C4]\n\t(No symbol) [0x00007FF72FFD63F6]\n\t(No symbol) [0x00007FF72FFC67A3]\n\tBaseThreadInitThunk [0x00007FFAEED47614+20]\n\tRtlUserThreadStart [0x00007FFAF02E26B1+33]\n","stackTrace":[{"declaringClass":"com.co.shein.stepsdefinitions.LoginStepDefiniton","methodName":"heUserEnterATheWebsite","fileName":"LoginStepDefiniton.java","lineNumber":31},{"declaringClass":"cucumber.runner.Runner","methodName":"runPickle","fileName":"Runner.java","lineNumber":80},{"declaringClass":"worker.org.gradle.process.internal.worker.GradleWorkerMain","methodName":"run","fileName":"GradleWorkerMain.java","lineNumber":69},{"declaringClass":"worker.org.gradle.process.internal.worker.GradleWorkerMain","methodName":"main","fileName":"GradleWorkerMain.java","lineNumber":74}]}}},"result":"ERROR","precondition":false,"level":1}]},{"number":3,"description":"When the user select a product and the agregate a carrito for delete","duration":2,"startTime":"2023-09-19T16:48:10.468-05:00[America/Bogota]","result":"SKIPPED","precondition":false,"level":0},{"number":4,"description":"Then the user see that not there is products","duration":1,"startTime":"2023-09-19T16:48:10.471-05:00[America/Bogota]","result":"SKIPPED","precondition":false,"level":0}],"userStory":{"id":"buylaptop","storyName":"BuyLaptop","path":"src/test/resources/features/buyLaptop.feature","narrative":"  i need buy a Laptod","type":"feature"},"featureTag":{"name":"Features/BuyLaptop","type":"feature","displayName":"Features/BuyLaptop"},"title":"Eliminate a product","tags":[{"name":"BuyLaptop","type":"feature","displayName":"BuyLaptop"}],"startTime":"2023-09-19T16:48:09.607-05:00[America/Bogota]","duration":866,"testFailureCause":{"errorType":"net.thucydides.core.webdriver.DriverConfigurationError","message":"Could not instantiate new WebDriver instance of type class org.openqa.selenium.chrome.ChromeDriver (unknown error: failed to write prefs file\nBuild info: version: \u00273.141.59\u0027, revision: \u0027e82be7d358\u0027, time: \u00272018-11-14T08:17:03\u0027\nSystem info: host: \u0027DESKTOP-SN1JVCC\u0027, ip: \u0027192.168.56.1\u0027, os.name: \u0027Windows 10\u0027, os.arch: \u0027amd64\u0027, os.version: \u002710.0\u0027, java.version: \u00271.8.0_161\u0027\nDriver info: driver.version: ProvideNewDriver\nremote stacktrace: \tGetHandleVerifier [0x00007FF7300552A2+57122]\n\t(No symbol) [0x00007FF72FFCEA92]\n\t(No symbol) [0x00007FF72FE9E3AB]\n\t(No symbol) [0x00007FF72FEC8F12]\n\t(No symbol) [0x00007FF72FEC9201]\n\t(No symbol) [0x00007FF72FEC610F]\n\t(No symbol) [0x00007FF72FEC2FE1]\n\t(No symbol) [0x00007FF72FEFEA4F]\n\t(No symbol) [0x00007FF72FEFE5B0]\n\t(No symbol) [0x00007FF72FEF6DB3]\n\t(No symbol) [0x00007FF72FECD2B1]\n\t(No symbol) [0x00007FF72FECE494]\n\tGetHandleVerifier [0x00007FF7302FEF82+2849794]\n\tGetHandleVerifier [0x00007FF730351D24+3189156]\n\tGetHandleVerifier [0x00007FF73034ACAF+3160367]\n\tGetHandleVerifier [0x00007FF7300E6D06+653702]\n\t(No symbol) [0x00007FF72FFDA208]\n\t(No symbol) [0x00007FF72FFD62C4]\n\t(No symbol) [0x00007FF72FFD63F6]\n\t(No symbol) [0x00007FF72FFC67A3]\n\tBaseThreadInitThunk [0x00007FFAEED47614+20]\n\tRtlUserThreadStart [0x00007FFAF02E26B1+33]\n). See below for more details.","stackTrace":[{"declaringClass":"com.co.shein.stepsdefinitions.LoginStepDefiniton","methodName":"heUserEnterATheWebsite","fileName":"LoginStepDefiniton.java","lineNumber":31},{"declaringClass":"cucumber.runner.Runner","methodName":"runPickle","fileName":"Runner.java","lineNumber":80},{"declaringClass":"worker.org.gradle.process.internal.worker.GradleWorkerMain","methodName":"run","fileName":"GradleWorkerMain.java","lineNumber":69},{"declaringClass":"worker.org.gradle.process.internal.worker.GradleWorkerMain","methodName":"main","fileName":"GradleWorkerMain.java","lineNumber":74}],"rootCause":{"errorType":"org.openqa.selenium.WebDriverException","message":"unknown error: failed to write prefs file\nBuild info: version: \u00273.141.59\u0027, revision: \u0027e82be7d358\u0027, time: \u00272018-11-14T08:17:03\u0027\nSystem info: host: \u0027DESKTOP-SN1JVCC\u0027, ip: \u0027192.168.56.1\u0027, os.name: \u0027Windows 10\u0027, os.arch: \u0027amd64\u0027, os.version: \u002710.0\u0027, java.version: \u00271.8.0_161\u0027\nDriver info: driver.version: ProvideNewDriver\nremote stacktrace: \tGetHandleVerifier [0x00007FF7300552A2+57122]\n\t(No symbol) [0x00007FF72FFCEA92]\n\t(No symbol) [0x00007FF72FE9E3AB]\n\t(No symbol) [0x00007FF72FEC8F12]\n\t(No symbol) [0x00007FF72FEC9201]\n\t(No symbol) [0x00007FF72FEC610F]\n\t(No symbol) [0x00007FF72FEC2FE1]\n\t(No symbol) [0x00007FF72FEFEA4F]\n\t(No symbol) [0x00007FF72FEFE5B0]\n\t(No symbol) [0x00007FF72FEF6DB3]\n\t(No symbol) [0x00007FF72FECD2B1]\n\t(No symbol) [0x00007FF72FECE494]\n\tGetHandleVerifier [0x00007FF7302FEF82+2849794]\n\tGetHandleVerifier [0x00007FF730351D24+3189156]\n\tGetHandleVerifier [0x00007FF73034ACAF+3160367]\n\tGetHandleVerifier [0x00007FF7300E6D06+653702]\n\t(No symbol) [0x00007FF72FFDA208]\n\t(No symbol) [0x00007FF72FFD62C4]\n\t(No symbol) [0x00007FF72FFD63F6]\n\t(No symbol) [0x00007FF72FFC67A3]\n\tBaseThreadInitThunk [0x00007FFAEED47614+20]\n\tRtlUserThreadStart [0x00007FFAF02E26B1+33]\n","stackTrace":[{"declaringClass":"com.co.shein.stepsdefinitions.LoginStepDefiniton","methodName":"heUserEnterATheWebsite","fileName":"LoginStepDefiniton.java","lineNumber":31},{"declaringClass":"cucumber.runner.Runner","methodName":"runPickle","fileName":"Runner.java","lineNumber":80},{"declaringClass":"worker.org.gradle.process.internal.worker.GradleWorkerMain","methodName":"run","fileName":"GradleWorkerMain.java","lineNumber":69},{"declaringClass":"worker.org.gradle.process.internal.worker.GradleWorkerMain","methodName":"main","fileName":"GradleWorkerMain.java","lineNumber":74}]}},"testFailureClassname":"net.thucydides.core.webdriver.DriverConfigurationError","testFailureMessage":"Could not instantiate new WebDriver instance of type class org.openqa.selenium.chrome.ChromeDriver (unknown error: failed to write prefs file\nBuild info: version: \u00273.141.59\u0027, revision: \u0027e82be7d358\u0027, time: \u00272018-11-14T08:17:03\u0027\nSystem info: host: \u0027DESKTOP-SN1JVCC\u0027, ip: \u0027192.168.56.1\u0027, os.name: \u0027Windows 10\u0027, os.arch: \u0027amd64\u0027, os.version: \u002710.0\u0027, java.version: \u00271.8.0_161\u0027\nDriver info: driver.version: ProvideNewDriver\nremote stacktrace: \tGetHandleVerifier [0x00007FF7300552A2+57122]\n\t(No symbol) [0x00007FF72FFCEA92]\n\t(No symbol) [0x00007FF72FE9E3AB]\n\t(No symbol) [0x00007FF72FEC8F12]\n\t(No symbol) [0x00007FF72FEC9201]\n\t(No symbol) [0x00007FF72FEC610F]\n\t(No symbol) [0x00007FF72FEC2FE1]\n\t(No symbol) [0x00007FF72FEFEA4F]\n\t(No symbol) [0x00007FF72FEFE5B0]\n\t(No symbol) [0x00007FF72FEF6DB3]\n\t(No symbol) [0x00007FF72FECD2B1]\n\t(No symbol) [0x00007FF72FECE494]\n\tGetHandleVerifier [0x00007FF7302FEF82+2849794]\n\tGetHandleVerifier [0x00007FF730351D24+3189156]\n\tGetHandleVerifier [0x00007FF73034ACAF+3160367]\n\tGetHandleVerifier [0x00007FF7300E6D06+653702]\n\t(No symbol) [0x00007FF72FFDA208]\n\t(No symbol) [0x00007FF72FFD62C4]\n\t(No symbol) [0x00007FF72FFD63F6]\n\t(No symbol) [0x00007FF72FFC67A3]\n\tBaseThreadInitThunk [0x00007FFAEED47614+20]\n\tRtlUserThreadStart [0x00007FFAF02E26B1+33]\n). See below for more details.","testFailureSummary":"ERROR;net.thucydides.core.webdriver.DriverConfigurationError;Could not instantiate new WebDriver instance of type class org.openqa.selenium.chrome.ChromeDriver (unknown error: failed to write prefs file\nBuild info: version: \u00273.141.59\u0027, revision: \u0027e82be7d358\u0027, time: \u00272018-11-14T08:17:03\u0027\nSystem info: host: \u0027DESKTOP-SN1JVCC\u0027, ip: \u0027192.168.56.1\u0027, os.name: \u0027Windows 10\u0027, os.arch: \u0027amd64\u0027, os.version: \u002710.0\u0027, java.version: \u00271.8.0_161\u0027\nDriver info: driver.version: ProvideNewDriver\nremote stacktrace: \tGetHandleVerifier [0x00007FF7300552A2+57122]\n\t(No symbol) [0x00007FF72FFCEA92]\n\t(No symbol) [0x00007FF72FE9E3AB]\n\t(No symbol) [0x00007FF72FEC8F12]\n\t(No symbol) [0x00007FF72FEC9201]\n\t(No symbol) [0x00007FF72FEC610F]\n\t(No symbol) [0x00007FF72FEC2FE1]\n\t(No symbol) [0x00007FF72FEFEA4F]\n\t(No symbol) [0x00007FF72FEFE5B0]\n\t(No symbol) [0x00007FF72FEF6DB3]\n\t(No symbol) [0x00007FF72FECD2B1]\n\t(No symbol) [0x00007FF72FECE494]\n\tGetHandleVerifier [0x00007FF7302FEF82+2849794]\n\tGetHandleVerifier [0x00007FF730351D24+3189156]\n\tGetHandleVerifier [0x00007FF73034ACAF+3160367]\n\tGetHandleVerifier [0x00007FF7300E6D06+653702]\n\t(No symbol) [0x00007FF72FFDA208]\n\t(No symbol) [0x00007FF72FFD62C4]\n\t(No symbol) [0x00007FF72FFD63F6]\n\t(No symbol) [0x00007FF72FFC67A3]\n\tBaseThreadInitThunk [0x00007FFAEED47614+20]\n\tRtlUserThreadStart [0x00007FFAF02E26B1+33]\n). See below for more details.;LoginStepDefiniton.java","projectKey":"","annotatedResult":"ERROR","isManualTestingUpToDate":false,"manual":false,"testSource":"Cucumber","actors":[{"name":"Andres","can":["browse the web"]}],"result":"ERROR"}