{"name":"Agregate Phone Successfull","id":"buy-a-phone;agregate-phone-successfull","testSteps":[{"number":1,"description":"Given he user enter a the website","duration":6702,"startTime":"2023-09-19T22:44:32.692-05:00[America/Bogota]","screenshots":[{"screenshot":"d7b9233cbe018ee1a85856c31d51cacfe45d1f9e4e314944e6232d6639c6ec4e.png","timeStamp":1695181479394}],"result":"SUCCESS","precondition":false,"level":0,"children":[{"number":2,"description":"Andres opens the https://www.demoblaze.com/index.html","duration":6677,"startTime":"2023-09-19T22:44:32.697-05:00[America/Bogota]","screenshots":[{"screenshot":"d7b9233cbe018ee1a85856c31d51cacfe45d1f9e4e314944e6232d6639c6ec4e.png","timeStamp":1695181479373}],"result":"SUCCESS","precondition":false,"level":1}]},{"number":3,"description":"When the user select a phone and go to carrito","duration":21183,"startTime":"2023-09-19T22:44:39.395-05:00[America/Bogota]","screenshots":[{"screenshot":"5656aefd9db7a1b6368949dc7f7bf59b5d5a83c2b2551cb19c43ee05687c3fd8.png","timeStamp":1695181500578}],"result":"SUCCESS","precondition":false,"level":0,"children":[{"number":4,"description":"Andres phone task","duration":21124,"startTime":"2023-09-19T22:44:39.423-05:00[America/Bogota]","screenshots":[{"screenshot":"a8a5103086e0353eea1cca377300622fe1904834c85a3f615d8a3dc257cbab9c.png","timeStamp":1695181479777},{"screenshot":"5656aefd9db7a1b6368949dc7f7bf59b5d5a83c2b2551cb19c43ee05687c3fd8.png","timeStamp":1695181500547}],"result":"SUCCESS","precondition":false,"level":1,"children":[{"number":5,"description":"Andres clicks on ir al modulo de celulares","duration":673,"startTime":"2023-09-19T22:44:39.791-05:00[America/Bogota]","screenshots":[{"screenshot":"a8a5103086e0353eea1cca377300622fe1904834c85a3f615d8a3dc257cbab9c.png","timeStamp":1695181479818},{"screenshot":"f7e0583cc9e74e965d78bd3904e8cb5a7c0e013b4d4dd54b8a7a8da11942a1d4.png","timeStamp":1695181480464}],"result":"SUCCESS","precondition":false,"level":2},{"number":6,"description":"Andres clicks on seleccionar producto","duration":9628,"startTime":"2023-09-19T22:44:40.468-05:00[America/Bogota]","screenshots":[{"screenshot":"f7e0583cc9e74e965d78bd3904e8cb5a7c0e013b4d4dd54b8a7a8da11942a1d4.png","timeStamp":1695181480497},{"screenshot":"0bd553412de8a9d90e174a6c46a70f0b2550d4e557fc49a9713909bf61bba6a0.png","timeStamp":1695181490096}],"result":"SUCCESS","precondition":false,"level":2},{"number":7,"description":"Andres clicks on boton seleccionar","duration":803,"startTime":"2023-09-19T22:44:50.099-05:00[America/Bogota]","screenshots":[{"screenshot":"0bd553412de8a9d90e174a6c46a70f0b2550d4e557fc49a9713909bf61bba6a0.png","timeStamp":1695181490115},{"screenshot":"99486755449bab0aec950a2c5bb12ceb7e877c844eb215b55b2984f1b1e834c3.png","timeStamp":1695181490902}],"result":"SUCCESS","precondition":false,"level":2},{"number":8,"description":"Andres clicks on ir al carrito ","duration":1301,"startTime":"2023-09-19T22:44:54.910-05:00[America/Bogota]","screenshots":[{"screenshot":"3c75e53580afa48443274b690f88ea219ab11c5f6fa52f305b83c374feea8d8b.png","timeStamp":1695181496211}],"result":"SUCCESS","precondition":false,"level":2}]}]},{"number":9,"description":"Then the user will see his phone","duration":339,"startTime":"2023-09-19T22:45:00.580-05:00[America/Bogota]","screenshots":[{"screenshot":"5656aefd9db7a1b6368949dc7f7bf59b5d5a83c2b2551cb19c43ee05687c3fd8.png","timeStamp":1695181500919}],"result":"SUCCESS","precondition":false,"level":0}],"userStory":{"id":"buy-a-phone","storyName":"Buy a Phone","path":"src/test/resources/features/buyPhone.feature","narrative":"  i need buy a phone","type":"feature"},"featureTag":{"name":"Features/Buy a Phone","type":"feature","displayName":"Features/Buy a Phone"},"title":"Agregate Phone Successfull","tags":[{"name":"Buy a Phone","type":"feature","displayName":"Buy a Phone"}],"startTime":"2023-09-19T22:44:32.684-05:00[America/Bogota]","duration":28236,"projectKey":"","sessionId":"5fd876115912901df6f2c9b43d7cf36a","driver":"chrome","isManualTestingUpToDate":false,"manual":false,"testSource":"Cucumber","actors":[{"name":"Andres","can":["browse the web"]}],"result":"SUCCESS"}